{
  "staff": [
    {
      "name": "Ms Neha Jamwal",
      "file": "staff_certificates.pdf",
      "page": 1
    },
    {
      "name": "Ms Jeyoti Kaul",
      "file": "staff_certificates.pdf",
      "page": 2
    },
    {
      "name": "Mr Sunil Jamwal",
      "file": "staff_certificates.pdf",
      "page": 3
    },
    {
      "name": "Mr Arul Xavier",
      "file": "staff_certificates.pdf",
      "page": 4
    },
    {
      "name": "Mr Sumit Raj Gosh",
      "file": "staff_certificates.pdf",
      "page": 5
    },
    {
      "name": "Ms Richa Sharma",
      "file": "staff_certificates.pdf",
      "page": 6
    },
    {
      "name": "Ms Riddham Gupta",
      "file": "staff_certificates.pdf",
      "page": 7
    },
    {
      "name": "Ms Nandita Sharma",
      "file": "staff_certificates.pdf",
      "page": 8
    },
    {
      "name": "Dr Ram Prakash Prajapat",
      "file": "staff_certificates.pdf",
      "page": 9
    },
    {
      "name": "Mr Ankit Gupta",
      "file": "staff_certificates.pdf",
      "page": 10
    },
    {
      "name": "Mohammad Israil",
      "file": "staff_certificates.pdf",
      "page": 11
    },
    {
      "name": "Mohd Yaseen",
      "file": "staff_certificates.pdf",
      "page": 12
    },
    {
      "name": "Vishal Bagnehal",
      "file": "staff_certificates.pdf",
      "page": 13
    },
    {
      "name": "Himanshu Kumar",
      "file": "staff_certificates.pdf",
      "page": 14
    },
    {
      "name": "Rehana Rasool",
      "file": "staff_certificates.pdf",
      "page": 15
    },
    {
      "name": "Majid Bashir",
      "file": "staff_certificates.pdf",
      "page": 16
    },
    {
      "name": "Rohit Dogra",
      "file": "staff_certificates.pdf",
      "page": 17
    },
    {
      "name": "Adil Akbar",
      "file": "staff_certificates.pdf",
      "page": 18
    },
    {
      "name": "Gaurav Bhagat",
      "file": "staff_certificates.pdf",
      "page": 19
    },
    {
      "name": "Mohd Tabrez",
      "file": "staff_certificates.pdf",
      "page": 20
    },
    {
      "name": "Pooja Devi",
      "file": "staff_certificates.pdf",
      "page": 21
    },
    {
      "name": "Ajay Kumar",
      "file": "staff_certificates.pdf",
      "page": 22
    }
  ],
  "student": [
    {
      "name": "Arnav Bangroo",
      "project": "Smart Dustbin",
      "school": "Cambridge International school, Jammu",
      "file": "student_certificates.pdf",
      "page": 1
    },
    {
      "name": "Tansi Choudhary",
      "project": "Smart Irrigation System",
      "school": "Cambridge International school, Jammu",
      "file": "student_certificates.pdf",
      "page": 2
    },
    {
      "name": "Sumit Manhas",
      "project": "Smart Irrigation System",
      "school": "Cambridge International school, Jammu",
      "file": "student_certificates.pdf",
      "page": 3
    },
    {
      "name": "Sudanshu Sharma",
      "project": "Systemic Energy Generation Model ( Home -Based)",
      "school": "Cambridge International school, Jammu",
      "file": "student_certificates.pdf",
      "page": 4
    },
    {
      "name": "Farheen Choudhary",
      "project": "Systemic Energy Generation Model ( Home -Based)",
      "school": "Cambridge International school, Jammu",
      "file": "student_certificates.pdf",
      "page": 5
    },
    {
      "name": "Roshini  Sharma",
      "project": "Fresh Box and Gesture Gloves ( Aid for Deaf and Dumb)",
      "school": "Doon International  School, Jammu",
      "file": "student_certificates.pdf",
      "page": 6
    },
    {
      "name": "Ridha Sharma",
      "project": "Fresh Box and Gesture Gloves ( Aid for Deaf and Dumb)",
      "school": "Doon International  School, Jammu",
      "file": "student_certificates.pdf",
      "page": 7
    },
    {
      "name": "Sarish Choudhary",
      "project": "Fresh Box and Gesture Gloves ( Aid for Deaf and Dumb)",
      "school": "Doon International  School, Jammu",
      "file": "student_certificates.pdf",
      "page": 8
    },
    {
      "name": "Aadarsh  Pandey",
      "project": "Fresh Box and Gesture Gloves ( Aid for Deaf and Dumb)",
      "school": "Doon International  School, Jammu",
      "file": "student_certificates.pdf",
      "page": 9
    },
    {
      "name": "Arush Sharma",
      "project": "Fresh Box and Gesture Gloves ( Aid for Deaf and Dumb)",
      "school": "Doon International  School, Jammu",
      "file": "student_certificates.pdf",
      "page": 10
    },
    {
      "name": "Rukund Koul.",
      "project": "Fresh Box and Gesture Gloves ( Aid for Deaf and Dumb)",
      "school": "Doon International  School, Jammu",
      "file": "student_certificates.pdf",
      "page": 11
    },
    {
      "name": "Lakshita",
      "project": "Defendo gate, Smart Bridge and Smart Street Light",
      "school": "Army Public School Jammu Cantt",
      "file": "student_certificates.pdf",
      "page": 12
    },
    {
      "name": "Nikunj Jamwal",
      "project": "Defendo gate, Smart Bridge and Smart Street Light",
      "school": "Army Public School Jammu Cantt",
      "file": "student_certificates.pdf",
      "page": 13
    },
    {
      "name": "Kindeep Kour",
      "project": "Defendo gate, Smart Bridge and Smart Street Light",
      "school": "Army Public School Jammu Cantt",
      "file": "student_certificates.pdf",
      "page": 14
    },
    {
      "name": "Mst Ashai Ranjan",
      "project": "TransSafe AI- Future of Safe & Sustainable Transformers",
      "school": "ARMY PUBLIC SCHOOL RATNUCHAK, JAMMU (J&K)",
      "file": "student_certificates.pdf",
      "page": 15
    },
    {
      "name": "Mst Gourabpreet Singh",
      "project": "TransSafe AI- Future of Safe & Sustainable Transformers",
      "school": "ARMY PUBLIC SCHOOL RATNUCHAK, JAMMU (J&K)",
      "file": "student_certificates.pdf",
      "page": 16
    },
    {
      "name": "Mst Aditya Chaudhary",
      "project": "ECONEXUS- A Smart Waste Segregation System & FlyAsh Utilisation for Sustainable Road Repair",
      "school": "ARMY PUBLIC SCHOOL RATNUCHAK, JAMMU (J&K)",
      "file": "student_certificates.pdf",
      "page": 17
    },
    {
      "name": "Ms Sanskruti",
      "project": "ECONEXUS- A Smart Waste Segregation System & FlyAsh Utilisation for Sustainable Road Repair",
      "school": "ARMY PUBLIC SCHOOL RATNUCHAK, JAMMU (J&K)",
      "file": "student_certificates.pdf",
      "page": 18
    },
    {
      "name": "Manaswin Mahajan",
      "project": "Carbifier",
      "school": "Delhi Public School, Jammu",
      "file": "student_certificates.pdf",
      "page": 19
    },
    {
      "name": "Danish Talwar",
      "project": "Carbifier",
      "school": "Delhi Public School, Jammu",
      "file": "student_certificates.pdf",
      "page": 20
    },
    {
      "name": "Manya Targotra",
      "project": "Carbifier",
      "school": "Delhi Public School, Jammu",
      "file": "student_certificates.pdf",
      "page": 21
    },
    {
      "name": "Rudraksh Bargotra",
      "project": "Carbifier",
      "school": "Delhi Public School, Jammu",
      "file": "student_certificates.pdf",
      "page": 22
    },
    {
      "name": "Taransh Mahajan",
      "project": "Carbifier",
      "school": "Delhi Public School, Jammu",
      "file": "student_certificates.pdf",
      "page": 23
    },
    {
      "name": "Chaitanya Ghosh",
      "project": "RAPTOR",
      "school": "Delhi Public School Udhampur",
      "file": "student_certificates.pdf",
      "page": 24
    },
    {
      "name": "Sanchi Bhardwaj",
      "project": "RAPTOR",
      "school": "Delhi Public School Udhampur",
      "file": "student_certificates.pdf",
      "page": 25
    },
    {
      "name": "Aditya Thakur",
      "project": "RAPTOR",
      "school": "Delhi Public School Udhampur",
      "file": "student_certificates.pdf",
      "page": 26
    },
    {
      "name": "Sargam Mahajan",
      "project": "RAPTOR",
      "school": "Delhi Public School Udhampur",
      "file": "student_certificates.pdf",
      "page": 27
    },
    {
      "name": "Aayan Gupta",
      "project": "RAPTOR",
      "school": "Delhi Public School Udhampur",
      "file": "student_certificates.pdf",
      "page": 28
    },
    {
      "name": "Sanket",
      "project": "Portable Air Cooler,Portable Air Conditioner,DC Tester",
      "school": "Govt Girls High School Gandhinagar",
      "file": "student_certificates.pdf",
      "page": 29
    },
    {
      "name": "Khushi",
      "project": "Portable Air Cooler,Portable Air Conditioner,DC Tester",
      "school": "Govt Girls High School Gandhinagar",
      "file": "student_certificates.pdf",
      "page": 30
    },
    {
      "name": "PARI MEHRA",
      "project": "Water Level Indicator",
      "school": "Govt Girls High School Gandhinagar",
      "file": "student_certificates.pdf",
      "page": 31
    },
    {
      "name": "MANNAT KHOKHAR",
      "project": "Water Level Indicator",
      "school": "Govt Girls High School Gandhinagar",
      "file": "student_certificates.pdf",
      "page": 32
    },
    {
      "name": "KOMAL",
      "project": "Model for Centrifugal Force , Pull Back Car",
      "school": "Govt Girls High School Gandhinagar",
      "file": "student_certificates.pdf",
      "page": 33
    },
    {
      "name": "KOMAKSHI",
      "project": "Model for Centrifugal Force , Pull Back Car",
      "school": "Govt Girls High School Gandhinagar",
      "file": "student_certificates.pdf",
      "page": 34
    },
    {
      "name": "AHAAN MAHAJAN",
      "project": "Harnessing Power - The Future of Hybrid Solar Energy Systems",
      "school": "IDPS JAMMU",
      "file": "student_certificates.pdf",
      "page": 35
    },
    {
      "name": "TABISH RAZA",
      "project": "Harnessing Power - The Future of Hybrid Solar Energy Systems",
      "school": "IDPS JAMMU",
      "file": "student_certificates.pdf",
      "page": 36
    },
    {
      "name": "Diya Kumari",
      "project": "Transport System Model Supporting SDGs",
      "school": "JAMMU SANSKRITI SCHOOL, JAMMU",
      "file": "student_certificates.pdf",
      "page": 37
    },
    {
      "name": "Suhani Rana",
      "project": "Transport System Model Supporting SDGs",
      "school": "JAMMU SANSKRITI SCHOOL, JAMMU",
      "file": "student_certificates.pdf",
      "page": 38
    },
    {
      "name": "Keshvi Bhagat",
      "project": "Transport System Model Supporting SDGs",
      "school": "JAMMU SANSKRITI SCHOOL, JAMMU",
      "file": "student_certificates.pdf",
      "page": 39
    },
    {
      "name": "Daksh Chandel",
      "project": "Transport System Model Supporting SDGs",
      "school": "JAMMU SANSKRITI SCHOOL, JAMMU",
      "file": "student_certificates.pdf",
      "page": 40
    },
    {
      "name": "Aniket Chouhan",
      "project": "Transport System Model Supporting SDGs",
      "school": "JAMMU SANSKRITI SCHOOL, JAMMU",
      "file": "student_certificates.pdf",
      "page": 41
    },
    {
      "name": "Artharav Choudhary",
      "project": "Transport System Model Supporting SDGs",
      "school": "JAMMU SANSKRITI SCHOOL, JAMMU",
      "file": "student_certificates.pdf",
      "page": 42
    },
    {
      "name": "Sashwat",
      "project": "The Fog Net Model",
      "school": "Jammu Sanskriti School Kathua",
      "file": "student_certificates.pdf",
      "page": 43
    },
    {
      "name": "Pakeezah",
      "project": "The Fog Net Model",
      "school": "Jammu Sanskriti School Kathua",
      "file": "student_certificates.pdf",
      "page": 44
    },
    {
      "name": "Sehrish",
      "project": "The Fog Net Model",
      "school": "Jammu Sanskriti School Kathua",
      "file": "student_certificates.pdf",
      "page": 45
    },
    {
      "name": "Aksa",
      "project": "The Fog Net Model",
      "school": "Jammu Sanskriti School Kathua",
      "file": "student_certificates.pdf",
      "page": 46
    },
    {
      "name": "Sanidhya",
      "project": "The Fog Net Model",
      "school": "Jammu Sanskriti School Kathua",
      "file": "student_certificates.pdf",
      "page": 47
    },
    {
      "name": "Harsh Jamwal",
      "project": "The Fog Net Model",
      "school": "Jammu Sanskriti School Kathua",
      "file": "student_certificates.pdf",
      "page": 48
    },
    {
      "name": "Hardik Bhat",
      "project": "Era of Pleizoelectric tile",
      "school": "KC International School",
      "file": "student_certificates.pdf",
      "page": 49
    },
    {
      "name": "Agrim Banotra",
      "project": "Era of Pleizoelectric tile",
      "school": "KC International School",
      "file": "student_certificates.pdf",
      "page": 50
    },
    {
      "name": "Tanmauy Parimoo",
      "project": "Era of Pleizoelectric tile",
      "school": "KC International School",
      "file": "student_certificates.pdf",
      "page": 51
    },
    {
      "name": "Ananya Sharma",
      "project": "Mangalyaan",
      "school": "KC International School",
      "file": "student_certificates.pdf",
      "page": 52
    },
    {
      "name": "Akrit Singh Kotwal",
      "project": "Mangalyaan",
      "school": "KC International School",
      "file": "student_certificates.pdf",
      "page": 53
    },
    {
      "name": "Sanidhya Suri",
      "project": "Herba Papyrus",
      "school": "KC International School",
      "file": "student_certificates.pdf",
      "page": 54
    },
    {
      "name": "Atharav gupta",
      "project": "Gas Guard",
      "school": "Model Academy, B C  road Jammu",
      "file": "student_certificates.pdf",
      "page": 55
    },
    {
      "name": "Assad Malik",
      "project": "Gas Guard",
      "school": "Model Academy, B C  road Jammu",
      "file": "student_certificates.pdf",
      "page": 56
    },
    {
      "name": "Lovish",
      "project": "Gas Guard",
      "school": "Model Academy, B C  road Jammu",
      "file": "student_certificates.pdf",
      "page": 57
    },
    {
      "name": "Disha",
      "project": "Gas Guard",
      "school": "Model Academy, B C  road Jammu",
      "file": "student_certificates.pdf",
      "page": 58
    },
    {
      "name": "Anant",
      "project": "Gas Guard",
      "school": "Model Academy, B C  road Jammu",
      "file": "student_certificates.pdf",
      "page": 59
    },
    {
      "name": "prachi",
      "project": "Gas Guard",
      "school": "Model Academy, B C  road Jammu",
      "file": "student_certificates.pdf",
      "page": 60
    },
    {
      "name": "Prince sharma  Mentor",
      "project": "Gas Guard",
      "school": "Model Academy, B C  road Jammu",
      "file": "student_certificates.pdf",
      "page": 61
    },
    {
      "name": "Yashodhan verma",
      "project": "State Locator",
      "school": "Spring Dales English School, Changran (Kathua)",
      "file": "student_certificates.pdf",
      "page": 62
    },
    {
      "name": "Vidhan Sharma",
      "project": "Zap Shoe",
      "school": "Spring Dales English School, Changran (Kathua)",
      "file": "student_certificates.pdf",
      "page": 63
    },
    {
      "name": "Sachi Sharma",
      "project": "Aqua fina",
      "school": "Spring Dales English School, Changran (Kathua)",
      "file": "student_certificates.pdf",
      "page": 64
    },
    {
      "name": "Sadhya Sambyal",
      "project": "Aqua fina",
      "school": "Spring Dales English School, Changran (Kathua)",
      "file": "student_certificates.pdf",
      "page": 65
    },
    {
      "name": "Saundarya Rajput",
      "project": "Solar Combat Kit",
      "school": "Spring Dales English School, Changran (Kathua)",
      "file": "student_certificates.pdf",
      "page": 66
    },
    {
      "name": "Jagruti Sharma",
      "project": "Solar Combat Kit",
      "school": "Spring Dales English School, Changran (Kathua)",
      "file": "student_certificates.pdf",
      "page": 67
    },
    {
      "name": "Dakshesh Sharma",
      "project": "Cliff Guard Car",
      "school": "Spring Dales English School, Changran (Kathua)",
      "file": "student_certificates.pdf",
      "page": 68
    },
    {
      "name": "Sambhavi Mahajan",
      "project": "LiFi",
      "school": "The Shri Ram Universal School, Jakh Samba",
      "file": "student_certificates.pdf",
      "page": 69
    },
    {
      "name": "Shobit Mahajan",
      "project": "Digital Sandglass",
      "school": "The Shri Ram Universal School, Jakh Samba",
      "file": "student_certificates.pdf",
      "page": 70
    },
    {
      "name": "Hitesh Singh",
      "project": "Meeting Schedular",
      "school": "The Shri Ram Universal School, Jakh Samba",
      "file": "student_certificates.pdf",
      "page": 71
    },
    {
      "name": "Vaishnavi",
      "project": "RFID Door Lock System",
      "school": "The Shri Ram Universal School, Jakh Samba",
      "file": "student_certificates.pdf",
      "page": 72
    },
    {
      "name": "Mukteksha",
      "project": "Health Monitoring System",
      "school": "The Shri Ram Universal School, Jakh Samba",
      "file": "student_certificates.pdf",
      "page": 73
    },
    {
      "name": "Akshaj Chalotra",
      "project": "Smart Dustbin",
      "school": "The Shri Ram Universal School, Jakh Samba",
      "file": "student_certificates.pdf",
      "page": 74
    },
    {
      "name": "SHIVAM KUMAR",
      "project": "SMART BRIDGE",
      "school": "Sainik School Nagrota",
      "file": "student_certificates.pdf",
      "page": 75
    },
    {
      "name": "KRITI SHARMA",
      "project": "SMART BRIDGE",
      "school": "Sainik School Nagrota",
      "file": "student_certificates.pdf",
      "page": 76
    },
    {
      "name": "UTKARSH VIVEK",
      "project": "ANTI ACCIDENTAL GLASSES",
      "school": "Sainik School Nagrota",
      "file": "student_certificates.pdf",
      "page": 77
    },
    {
      "name": "NIVRITI NAAMYA",
      "project": "ANTI ACCIDENTAL GLASSES",
      "school": "Sainik School Nagrota",
      "file": "student_certificates.pdf",
      "page": 78
    },
    {
      "name": "PARTH SHARMA",
      "project": "BLIND STICK",
      "school": "Sainik School Nagrota",
      "file": "student_certificates.pdf",
      "page": 79
    },
    {
      "name": "RISHITA SINGH",
      "project": "BLIND STICK",
      "school": "Sainik School Nagrota",
      "file": "student_certificates.pdf",
      "page": 80
    },
    {
      "name": "AETISAM AIJAZ RESHI",
      "project": "RADAR DISPLAY",
      "school": "Sainik School Nagrota",
      "file": "student_certificates.pdf",
      "page": 81
    },
    {
      "name": "ANIKA SELOT",
      "project": "RADAR DISPLAY",
      "school": "Sainik School Nagrota",
      "file": "student_certificates.pdf",
      "page": 82
    },
    {
      "name": "ARYAN SHARMA",
      "project": "BLIND GOGGLES",
      "school": "Sainik School Nagrota",
      "file": "student_certificates.pdf",
      "page": 83
    },
    {
      "name": "RASHI YADAV",
      "project": "BLIND GOGGLES",
      "school": "Sainik School Nagrota",
      "file": "student_certificates.pdf",
      "page": 84
    },
    {
      "name": "RAJVEER RAKWAL",
      "project": "SMART BARRICADE",
      "school": "Sainik School Nagrota",
      "file": "student_certificates.pdf",
      "page": 85
    },
    {
      "name": "STANZIN ANGMO",
      "project": "SMART BARRICADE",
      "school": "Sainik School Nagrota",
      "file": "student_certificates.pdf",
      "page": 86
    },
    {
      "name": "SAI SANNIDHI MISHRA",
      "project": "RADAR DISPLAY",
      "school": "Sainik School Nagrota",
      "file": "student_certificates.pdf",
      "page": 87
    },
    {
      "name": "NAVNEET PARIHAR",
      "project": "DRONE DISPLAY",
      "school": "Sainik School Nagrota",
      "file": "student_certificates.pdf",
      "page": 88
    },
    {
      "name": "HIMANI SHARMA",
      "project": "DRONE DISPLAY",
      "school": "Sainik School Nagrota",
      "file": "student_certificates.pdf",
      "page": 89
    },
    {
      "name": "MEDHANSH SINGH",
      "project": "DRONE DISPLAY",
      "school": "Sainik School Nagrota",
      "file": "student_certificates.pdf",
      "page": 90
    },
    {
      "name": "KEVIN JIBEN",
      "project": "SMART BARRICADE",
      "school": "Sainik School Nagrota",
      "file": "student_certificates.pdf",
      "page": 91
    }
  ],
  "volunteer": [
    {
      "name": "Ashutosh Vishwakarma",
      "designation": "Coordinator",
      "file": "volunteer_certificates.pdf",
      "page": 1
    },
    {
      "name": "Nipun Singh",
      "designation": "Hospitality Team Head",
      "file": "volunteer_certificates.pdf",
      "page": 2
    },
    {
      "name": "Aryan Sheel",
      "designation": "Technical Team Head",
      "file": "volunteer_certificates.pdf",
      "page": 3
    },
    {
      "name": "Raghav Jaiman",
      "designation": "Arts Team Head",
      "file": "volunteer_certificates.pdf",
      "page": 4
    },
    {
      "name": "Vaishnavi Singh",
      "designation": "Arts Team Head",
      "file": "volunteer_certificates.pdf",
      "page": 5
    },
    {
      "name": "Vishal Kumar",
      "designation": "Security Head",
      "file": "volunteer_certificates.pdf",
      "page": 6
    },
    {
      "name": "Vivek Sawalkar",
      "designation": "Infrastructre and Logistic Team Head",
      "file": "volunteer_certificates.pdf",
      "page": 7
    },
    {
      "name": "Vibhu Gupta",
      "designation": "Infrastructre and Logistic Team Head",
      "file": "volunteer_certificates.pdf",
      "page": 8
    },
    {
      "name": "Devesh Sharma",
      "designation": "Design Team Head",
      "file": "volunteer_certificates.pdf",
      "page": 9
    },
    {
      "name": "Yash Faujdar",
      "designation": "Coverage Team Head",
      "file": "volunteer_certificates.pdf",
      "page": 10
    },
    {
      "name": "Rahul Kumar",
      "designation": "Public Relation Team Head",
      "file": "volunteer_certificates.pdf",
      "page": 11
    },
    {
      "name": "Aryan Raj",
      "designation": "Web Development Team Head",
      "file": "volunteer_certificates.pdf",
      "page": 12
    },
    {
      "name": "Rohan Sahu",
      "designation": "ATL Experiment Demonstration Head",
      "file": "volunteer_certificates.pdf",
      "page": 13
    },
    {
      "name": "Siddhartha",
      "designation": "ATL Experiment Demonstration Volunteer",
      "file": "volunteer_certificates.pdf",
      "page": 14
    },
    {
      "name": "Udharav Kesar",
      "designation": "ATL Experiment Demonstration Volunteer",
      "file": "volunteer_certificates.pdf",
      "page": 15
    },
    {
      "name": "Vivek Chaudhary",
      "designation": "ATL Experiment Demonstration Volunteer",
      "file": "volunteer_certificates.pdf",
      "page": 16
    },
    {
      "name": "Sandeep",
      "designation": "ATL Experiment Demonstration Volunteer",
      "file": "volunteer_certificates.pdf",
      "page": 17
    },
    {
      "name": "Karan Singla",
      "designation": "ATL Experiment Demonstration Volunteer",
      "file": "volunteer_certificates.pdf",
      "page": 18
    },
    {
      "name": "Krishna",
      "designation": "ATL Experiment Demonstration Volunteer",
      "file": "volunteer_certificates.pdf",
      "page": 19
    },
    {
      "name": "Saksham vijay",
      "designation": "ATL Experiment Demonstration Volunteer",
      "file": "volunteer_certificates.pdf",
      "page": 20
    },
    {
      "name": "Adarsh Jha",
      "designation": "ATL Experiment Demonstration Volunteer",
      "file": "volunteer_certificates.pdf",
      "page": 21
    },
    {
      "name": "Amit Kumar",
      "designation": "ATL Experiment Demonstration Volunteer",
      "file": "volunteer_certificates.pdf",
      "page": 22
    },
    {
      "name": "Abhay",
      "designation": "ATL Experiment Demonstration Volunteer",
      "file": "volunteer_certificates.pdf",
      "page": 23
    },
    {
      "name": "Vardan Joshi",
      "designation": "ATL Experiment Demonstration Volunteer",
      "file": "volunteer_certificates.pdf",
      "page": 24
    },
    {
      "name": "Dhruv Singh",
      "designation": "Artificial Intelligence Demonstration Head",
      "file": "volunteer_certificates.pdf",
      "page": 25
    },
    {
      "name": "Sayuj Gupta",
      "designation": "Artificial Intelligence Demonstration Volunteer",
      "file": "volunteer_certificates.pdf",
      "page": 26
    },
    {
      "name": "Sahil",
      "designation": "Artificial Intelligence Demonstration Volunteer",
      "file": "volunteer_certificates.pdf",
      "page": 27
    },
    {
      "name": "Chaitanya Tandon",
      "designation": "Artificial Intelligence Demonstration Volunteer",
      "file": "volunteer_certificates.pdf",
      "page": 28
    },
    {
      "name": "Kartik Dua",
      "designation": "Artificial Intelligence Demonstration Volunteer",
      "file": "volunteer_certificates.pdf",
      "page": 29
    },
    {
      "name": "Priyanshi Agarwal",
      "designation": "Artificial Intelligence Demonstration Volunteer",
      "file": "volunteer_certificates.pdf",
      "page": 30
    },
    {
      "name": "Rajul Tyagi",
      "designation": "Artificial Intelligence Demonstration Volunteer",
      "file": "volunteer_certificates.pdf",
      "page": 31
    },
    {
      "name": "Heetkumar Kaneriya",
      "designation": "Robotics Demonstration Head",
      "file": "volunteer_certificates.pdf",
      "page": 32
    },
    {
      "name": "Patel Prit",
      "designation": "Robotics Demonstration Volunteer",
      "file": "volunteer_certificates.pdf",
      "page": 33
    },
    {
      "name": "Drish Mahajan",
      "designation": "Robotics Demonstration Volunteer",
      "file": "volunteer_certificates.pdf",
      "page": 34
    },
    {
      "name": "Purushartha Gupta",
      "designation": "Robotics Demonstration Volunteer",
      "file": "volunteer_certificates.pdf",
      "page": 35
    },
    {
      "name": "Aman Nagar",
      "designation": "Robotics Demonstration Volunteer",
      "file": "volunteer_certificates.pdf",
      "page": 36
    },
    {
      "name": "Ayush Bechara",
      "designation": "Robotics Demonstration Volunteer",
      "file": "volunteer_certificates.pdf",
      "page": 37
    },
    {
      "name": "Ujjwal Vishwakarma",
      "designation": "Robotics Demonstration Volunteer",
      "file": "volunteer_certificates.pdf",
      "page": 38
    },
    {
      "name": "Yuvraj Motiramani",
      "designation": "Robotics Demonstration Volunteer",
      "file": "volunteer_certificates.pdf",
      "page": 39
    },
    {
      "name": "Parth Sachdeva",
      "designation": "Robotics Demonstration Volunteer",
      "file": "volunteer_certificates.pdf",
      "page": 40
    },
    {
      "name": "Sahil",
      "designation": "Hands-on Tinkering Head",
      "file": "volunteer_certificates.pdf",
      "page": 41
    },
    {
      "name": "Bhanu Pratap",
      "designation": "Hands-on Tinkering Volunteer",
      "file": "volunteer_certificates.pdf",
      "page": 42
    },
    {
      "name": "Aryan Singh",
      "designation": "Hands-on Tinkering Volunteer",
      "file": "volunteer_certificates.pdf",
      "page": 43
    },
    {
      "name": "Yash",
      "designation": "Hands-on Tinkering Volunteer",
      "file": "volunteer_certificates.pdf",
      "page": 44
    },
    {
      "name": "Subhasis Malik",
      "designation": "Hands-on Tinkering Volunteer",
      "file": "volunteer_certificates.pdf",
      "page": 45
    },
    {
      "name": "Rahul Das",
      "designation": "Hands-on Tinkering Volunteer",
      "file": "volunteer_certificates.pdf",
      "page": 46
    },
    {
      "name": "Adwait Deshpande",
      "designation": "Hands-on Tinkering Volunteer",
      "file": "volunteer_certificates.pdf",
      "page": 47
    },
    {
      "name": "Yatindra Shukla",
      "designation": "Hands-on Tinkering Volunteer",
      "file": "volunteer_certificates.pdf",
      "page": 48
    },
    {
      "name": "Chethan Sai Kumar",
      "designation": "Hands-on Tinkering Volunteer",
      "file": "volunteer_certificates.pdf",
      "page": 49
    },
    {
      "name": "Bhavishya",
      "designation": "Hands-on Tinkering Volunteer",
      "file": "volunteer_certificates.pdf",
      "page": 50
    },
    {
      "name": "Rachit Goel",
      "designation": "Hands-on Tinkering Volunteer",
      "file": "volunteer_certificates.pdf",
      "page": 51
    },
    {
      "name": "Ronak Bagri",
      "designation": "Hands-on Tinkering Volunteer",
      "file": "volunteer_certificates.pdf",
      "page": 52
    },
    {
      "name": "Kshitij Aryan",
      "designation": "Hands-on Tinkering Volunteer",
      "file": "volunteer_certificates.pdf",
      "page": 53
    },
    {
      "name": "Harsh Singh",
      "designation": "Hands-on Tinkering Volunteer",
      "file": "volunteer_certificates.pdf",
      "page": 54
    },
    {
      "name": "Aman Kumar",
      "designation": "AR/VR Demonstration Head",
      "file": "volunteer_certificates.pdf",
      "page": 55
    },
    {
      "name": "Chetan Singh Adhikari",
      "designation": "AR/VR Demonstration Volunteer",
      "file": "volunteer_certificates.pdf",
      "page": 56
    },
    {
      "name": "Dhanay Aggarwal",
      "designation": "AR/VR Demonstration Volunteer",
      "file": "volunteer_certificates.pdf",
      "page": 57
    },
    {
      "name": "Meet Borisagar",
      "designation": "AR/VR Demonstration Volunteer",
      "file": "volunteer_certificates.pdf",
      "page": 58
    },
    {
      "name": "Harsh Neema",
      "designation": "AR/VR Demonstration Volunteer",
      "file": "volunteer_certificates.pdf",
      "page": 59
    },
    {
      "name": "Vraj Patel",
      "designation": "AR/VR Demonstration Volunteer",
      "file": "volunteer_certificates.pdf",
      "page": 60
    },
    {
      "name": "Harshad Shingde",
      "designation": "Drone Demonstration Head",
      "file": "volunteer_certificates.pdf",
      "page": 61
    },
    {
      "name": "Hriday Rana",
      "designation": "Drone Demonstration Volunteer",
      "file": "volunteer_certificates.pdf",
      "page": 62
    },
    {
      "name": "Owais Ansar",
      "designation": "Drone Demonstration Volunteer",
      "file": "volunteer_certificates.pdf",
      "page": 63
    },
    {
      "name": "Dhruv Poonia",
      "designation": "Drone Demonstration Volunteer",
      "file": "volunteer_certificates.pdf",
      "page": 64
    },
    {
      "name": "Aayush Singh",
      "designation": "Drone Demonstration Volunteer",
      "file": "volunteer_certificates.pdf",
      "page": 65
    },
    {
      "name": "Parth Sachdeva",
      "designation": "Drone Demonstration Volunteer",
      "file": "volunteer_certificates.pdf",
      "page": 66
    },
    {
      "name": "Ian Urade",
      "designation": "Drone Demonstration Volunteer",
      "file": "volunteer_certificates.pdf",
      "page": 67
    },
    {
      "name": "Kunjan Bansal",
      "designation": "Drone Demonstration Volunteer",
      "file": "volunteer_certificates.pdf",
      "page": 68
    },
    {
      "name": "Sunny Kumar",
      "designation": "Astronomy Demonstration Head",
      "file": "volunteer_certificates.pdf",
      "page": 69
    },
    {
      "name": "Abhibhav Aditya",
      "designation": "Astronomy Demonstration Volunteer",
      "file": "volunteer_certificates.pdf",
      "page": 70
    },
    {
      "name": "Harsh Kumar",
      "designation": "Astronomy Demonstration Volunteer",
      "file": "volunteer_certificates.pdf",
      "page": 71
    },
    {
      "name": "Sawan Rawat",
      "designation": "Astronomy Demonstration Volunteer",
      "file": "volunteer_certificates.pdf",
      "page": 72
    },
    {
      "name": "Deekshitha Sarilla",
      "designation": "Astronomy Demonstration Volunteer",
      "file": "volunteer_certificates.pdf",
      "page": 73
    },
    {
      "name": "Rohit",
      "designation": "Astronomy Demonstration Volunteer",
      "file": "volunteer_certificates.pdf",
      "page": 74
    },
    {
      "name": "Gajula Omkar",
      "designation": "Astronomy Demonstration Volunteer",
      "file": "volunteer_certificates.pdf",
      "page": 75
    },
    {
      "name": "Kummara Harshavardhan",
      "designation": "Astronomy Demonstration Volunteer",
      "file": "volunteer_certificates.pdf",
      "page": 76
    },
    {
      "name": "Shlok Tiwari",
      "designation": "Astronomy Demonstration Volunteer",
      "file": "volunteer_certificates.pdf",
      "page": 77
    },
    {
      "name": "Vaibhav Mittal",
      "designation": "Astronomy Demonstration Volunteer",
      "file": "volunteer_certificates.pdf",
      "page": 78
    },
    {
      "name": "Sparsh Dubey",
      "designation": "Astronomy Demonstration Volunteer",
      "file": "volunteer_certificates.pdf",
      "page": 79
    },
    {
      "name": "Rahul Kumar",
      "designation": "Astronomy Demonstration Volunteer",
      "file": "volunteer_certificates.pdf",
      "page": 80
    },
    {
      "name": "Shraddha Khanapurkar",
      "designation": "Astronomy Demonstration Volunteer",
      "file": "volunteer_certificates.pdf",
      "page": 81
    },
    {
      "name": "Sneha Hansrajani",
      "designation": "Astronomy Demonstration Volunteer",
      "file": "volunteer_certificates.pdf",
      "page": 82
    },
    {
      "name": "Soham Kakkar",
      "designation": "Astronomy Demonstration Volunteer",
      "file": "volunteer_certificates.pdf",
      "page": 83
    },
    {
      "name": "Prachi Sisodia",
      "designation": "Elocution Event Head",
      "file": "volunteer_certificates.pdf",
      "page": 84
    },
    {
      "name": "Kiran",
      "designation": "Elocution Event Volunteer",
      "file": "volunteer_certificates.pdf",
      "page": 85
    },
    {
      "name": "Anshika Singh",
      "designation": "Elocution Event Volunteer",
      "file": "volunteer_certificates.pdf",
      "page": 86
    },
    {
      "name": "Khushi",
      "designation": "Elocution Event Volunteer",
      "file": "volunteer_certificates.pdf",
      "page": 87
    },
    {
      "name": "Manjot Kaur",
      "designation": "Painting Event Head",
      "file": "volunteer_certificates.pdf",
      "page": 88
    },
    {
      "name": "Akshat Rai",
      "designation": "Painting Event Volunteer",
      "file": "volunteer_certificates.pdf",
      "page": 89
    },
    {
      "name": "Ayush Jha",
      "designation": "Painting Event Volunteer",
      "file": "volunteer_certificates.pdf",
      "page": 90
    },
    {
      "name": "Dhruv Khanna",
      "designation": "Painting Event Volunteer",
      "file": "volunteer_certificates.pdf",
      "page": 91
    },
    {
      "name": "Priyanshi Aggarwal",
      "designation": "Painting Event Volunteer",
      "file": "volunteer_certificates.pdf",
      "page": 92
    },
    {
      "name": "Basit",
      "designation": "Painting Event Volunteer",
      "file": "volunteer_certificates.pdf",
      "page": 93
    },
    {
      "name": "Hriday Jain",
      "designation": "Painting Event Volunteer",
      "file": "volunteer_certificates.pdf",
      "page": 94
    },
    {
      "name": "Aayush",
      "designation": "Painting Event Volunteer",
      "file": "volunteer_certificates.pdf",
      "page": 95
    },
    {
      "name": "Prisha Suchak",
      "designation": "Bracelet Making Event Head",
      "file": "volunteer_certificates.pdf",
      "page": 96
    },
    {
      "name": "Hardik Gupta",
      "designation": "Bracelet Making Event Volunteer",
      "file": "volunteer_certificates.pdf",
      "page": 97
    },
    {
      "name": "Ram",
      "designation": "Bracelet Making Event Volunteer",
      "file": "volunteer_certificates.pdf",
      "page": 98
    },
    {
      "name": "Ansh Bharadwaj",
      "designation": "Bracelet Making Event Volunteer",
      "file": "volunteer_certificates.pdf",
      "page": 99
    },
    {
      "name": "Nand Naman",
      "designation": "IITian Interaction Event Head",
      "file": "volunteer_certificates.pdf",
      "page": 100
    },
    {
      "name": "Sayuj Gupta",
      "designation": "IITian Interaction Event Volunteer",
      "file": "volunteer_certificates.pdf",
      "page": 101
    },
    {
      "name": "Raja Rajat Bhardwaj",
      "designation": "IITian Interaction Event Volunteer",
      "file": "volunteer_certificates.pdf",
      "page": 102
    },
    {
      "name": "Jashan Kumar",
      "designation": "IITian Interaction Event Volunteer",
      "file": "volunteer_certificates.pdf",
      "page": 103
    },
    {
      "name": "Isha Singh",
      "designation": "IITian Interaction Event Volunteer",
      "file": "volunteer_certificates.pdf",
      "page": 104
    },
    {
      "name": "Adwait Aditya",
      "designation": "IITian Interaction Event Volunteer",
      "file": "volunteer_certificates.pdf",
      "page": 105
    },
    {
      "name": "Vikrant Lalhal",
      "designation": "Documentary Show Event Head",
      "file": "volunteer_certificates.pdf",
      "page": 106
    },
    {
      "name": "Hardik Gupta",
      "designation": "Documentary Show Event Volunteer",
      "file": "volunteer_certificates.pdf",
      "page": 107
    },
    {
      "name": "Tanmay sharma",
      "designation": "Documentary Show Event Volunteer",
      "file": "volunteer_certificates.pdf",
      "page": 108
    },
    {
      "name": "Kovid Baid",
      "designation": "Documentary Show Event Volunteer",
      "file": "volunteer_certificates.pdf",
      "page": 109
    },
    {
      "name": "Shreshth Thapa",
      "designation": "Documentary Show Event Volunteer",
      "file": "volunteer_certificates.pdf",
      "page": 110
    },
    {
      "name": "Urvashi Gupta",
      "designation": "Jig-Saw Puzzle Solvinng Event Head",
      "file": "volunteer_certificates.pdf",
      "page": 111
    },
    {
      "name": "Hardik Gupta",
      "designation": "Jig-Saw Puzzle Solvinng Event Volunteer",
      "file": "volunteer_certificates.pdf",
      "page": 112
    },
    {
      "name": "Tanmay sharma",
      "designation": "Jig-Saw Puzzle Solvinng Event Volunteer",
      "file": "volunteer_certificates.pdf",
      "page": 113
    },
    {
      "name": "Kovid Baid",
      "designation": "Jig-Saw Puzzle Solvinng Event Volunteer",
      "file": "volunteer_certificates.pdf",
      "page": 114
    },
    {
      "name": "Prakhar Dwivedi",
      "designation": "Science Fair Management Head",
      "file": "volunteer_certificates.pdf",
      "page": 115
    },
    {
      "name": "Vijay Kumar",
      "designation": "Science Fair Management Volunteer",
      "file": "volunteer_certificates.pdf",
      "page": 116
    },
    {
      "name": "Owais Ansar",
      "designation": "Science Fair Management Volunteer",
      "file": "volunteer_certificates.pdf",
      "page": 117
    },
    {
      "name": "Mehul Gupta",
      "designation": "Science Fair Management Volunteer",
      "file": "volunteer_certificates.pdf",
      "page": 118
    },
    {
      "name": "Ayush Sharma",
      "designation": "Science Fair Management Volunteer",
      "file": "volunteer_certificates.pdf",
      "page": 119
    },
    {
      "name": "Sarvesh Prajapati",
      "designation": "Hospitality Team Volunteer",
      "file": "volunteer_certificates.pdf",
      "page": 120
    },
    {
      "name": "Anshika kukreja",
      "designation": "Hospitality Team Volunteer",
      "file": "volunteer_certificates.pdf",
      "page": 121
    },
    {
      "name": "Kannika Hebbar",
      "designation": "Hospitality Team Volunteer",
      "file": "volunteer_certificates.pdf",
      "page": 122
    },
    {
      "name": "Shubham Kumar",
      "designation": "Hospitality Team Volunteer",
      "file": "volunteer_certificates.pdf",
      "page": 123
    },
    {
      "name": "Kanhaiyalal",
      "designation": "Hospitality Team Volunteer",
      "file": "volunteer_certificates.pdf",
      "page": 124
    },
    {
      "name": "Shruti Venkatesh Embalwar",
      "designation": "Hospitality Team Volunteer",
      "file": "volunteer_certificates.pdf",
      "page": 125
    },
    {
      "name": "Anushka agarwal",
      "designation": "Hospitality Team Volunteer",
      "file": "volunteer_certificates.pdf",
      "page": 126
    },
    {
      "name": "Anushka",
      "designation": "Hospitality Team Volunteer",
      "file": "volunteer_certificates.pdf",
      "page": 127
    },
    {
      "name": "Mehak Garg",
      "designation": "Hospitality Team Volunteer",
      "file": "volunteer_certificates.pdf",
      "page": 128
    },
    {
      "name": "Payal Sharma",
      "designation": "Hospitality Team Volunteer",
      "file": "volunteer_certificates.pdf",
      "page": 129
    },
    {
      "name": "Riyaz khan",
      "designation": "Hospitality Team Volunteer",
      "file": "volunteer_certificates.pdf",
      "page": 130
    },
    {
      "name": "Kiran Sehrawat",
      "designation": "Hospitality Team Volunteer",
      "file": "volunteer_certificates.pdf",
      "page": 131
    },
    {
      "name": "Kanishka Chholak",
      "designation": "Hospitality Team Volunteer",
      "file": "volunteer_certificates.pdf",
      "page": 132
    },
    {
      "name": "Rudransh ghosh",
      "designation": "Hospitality Team Volunteer",
      "file": "volunteer_certificates.pdf",
      "page": 133
    },
    {
      "name": "Aditi kondal",
      "designation": "Hospitality Team Volunteer",
      "file": "volunteer_certificates.pdf",
      "page": 134
    },
    {
      "name": "Prasanna",
      "designation": "Hospitality Team Volunteer",
      "file": "volunteer_certificates.pdf",
      "page": 135
    },
    {
      "name": "Kashish",
      "designation": "Hospitality Team Volunteer",
      "file": "volunteer_certificates.pdf",
      "page": 136
    },
    {
      "name": "Suhan Salim",
      "designation": "Hospitality Team Volunteer",
      "file": "volunteer_certificates.pdf",
      "page": 137
    },
    {
      "name": "Siddharth Kumar",
      "designation": "Hospitality Team Volunteer",
      "file": "volunteer_certificates.pdf",
      "page": 138
    },
    {
      "name": "Md Nafis",
      "designation": "Hospitality Team Volunteer",
      "file": "volunteer_certificates.pdf",
      "page": 139
    },
    {
      "name": "Prateek Singh",
      "designation": "Hospitality Team Volunteer",
      "file": "volunteer_certificates.pdf",
      "page": 140
    },
    {
      "name": "Palak",
      "designation": "Hospitality Team Volunteer",
      "file": "volunteer_certificates.pdf",
      "page": 141
    },
    {
      "name": "Komal Kumari",
      "designation": "Hospitality Team Volunteer",
      "file": "volunteer_certificates.pdf",
      "page": 142
    },
    {
      "name": "Ujjwal",
      "designation": "Hospitality Team Volunteer",
      "file": "volunteer_certificates.pdf",
      "page": 143
    },
    {
      "name": "Mohit Yadav",
      "designation": "Hospitality Team Volunteer",
      "file": "volunteer_certificates.pdf",
      "page": 144
    },
    {
      "name": "Abhineet Kumar",
      "designation": "Hospitality Team Volunteer",
      "file": "volunteer_certificates.pdf",
      "page": 145
    },
    {
      "name": "Bhoomi Yadav",
      "designation": "Hospitality Team Volunteer",
      "file": "volunteer_certificates.pdf",
      "page": 146
    },
    {
      "name": "Anuj Saxena",
      "designation": "Hospitality Team Volunteer",
      "file": "volunteer_certificates.pdf",
      "page": 147
    },
    {
      "name": "Pranav Korhale",
      "designation": "Security Team Volunteer",
      "file": "volunteer_certificates.pdf",
      "page": 148
    },
    {
      "name": "Ruthwik",
      "designation": "Security Team Volunteer",
      "file": "volunteer_certificates.pdf",
      "page": 149
    },
    {
      "name": "Pavvan Seelam",
      "designation": "Security Team Volunteer",
      "file": "volunteer_certificates.pdf",
      "page": 150
    },
    {
      "name": "Sukka Rohith",
      "designation": "Security Team Volunteer",
      "file": "volunteer_certificates.pdf",
      "page": 151
    },
    {
      "name": "Ansh Agrawal",
      "designation": "Security Team Volunteer",
      "file": "volunteer_certificates.pdf",
      "page": 152
    },
    {
      "name": "Venu Naik Sugali",
      "designation": "Security Team Volunteer",
      "file": "volunteer_certificates.pdf",
      "page": 153
    },
    {
      "name": "Yagnesh Purini",
      "designation": "Security Team Volunteer",
      "file": "volunteer_certificates.pdf",
      "page": 154
    },
    {
      "name": "Tanuj Kumar",
      "designation": "Security Team Volunteer",
      "file": "volunteer_certificates.pdf",
      "page": 155
    },
    {
      "name": "Sai Subrahmanyam",
      "designation": "Security Team Volunteer",
      "file": "volunteer_certificates.pdf",
      "page": 156
    },
    {
      "name": "Meripr Jephan Sam",
      "designation": "Security Team Volunteer",
      "file": "volunteer_certificates.pdf",
      "page": 157
    },
    {
      "name": "Uma Shankar Sharma",
      "designation": "Security Team Volunteer",
      "file": "volunteer_certificates.pdf",
      "page": 158
    },
    {
      "name": "Satish",
      "designation": "Security Team Volunteer",
      "file": "volunteer_certificates.pdf",
      "page": 159
    },
    {
      "name": "Aayushman jadon",
      "designation": "Security Team Volunteer",
      "file": "volunteer_certificates.pdf",
      "page": 160
    },
    {
      "name": "Aradhya Sharma",
      "designation": "Security Team Volunteer",
      "file": "volunteer_certificates.pdf",
      "page": 161
    },
    {
      "name": "Chethan",
      "designation": "Security Team Volunteer",
      "file": "volunteer_certificates.pdf",
      "page": 162
    },
    {
      "name": "Dev Sahu",
      "designation": "Security Team Volunteer",
      "file": "volunteer_certificates.pdf",
      "page": 163
    },
    {
      "name": "Vikash Kumar Singh",
      "designation": "Security Team Volunteer",
      "file": "volunteer_certificates.pdf",
      "page": 164
    },
    {
      "name": "Navneet Choudhary",
      "designation": "Design Team Volunteer",
      "file": "volunteer_certificates.pdf",
      "page": 165
    },
    {
      "name": "Bhoomi Yadav",
      "designation": "Design Team Volunteer",
      "file": "volunteer_certificates.pdf",
      "page": 166
    },
    {
      "name": "Shreysa",
      "designation": "Design Team Volunteer",
      "file": "volunteer_certificates.pdf",
      "page": 167
    },
    {
      "name": "Misti Dharmeshkumar Shah",
      "designation": "Design Team Volunteer",
      "file": "volunteer_certificates.pdf",
      "page": 168
    },
    {
      "name": "Yashan Garg",
      "designation": "Design Team Volunteer",
      "file": "volunteer_certificates.pdf",
      "page": 169
    },
    {
      "name": "Jay Mangal Pandey",
      "designation": "Design Team Volunteer",
      "file": "volunteer_certificates.pdf",
      "page": 170
    },
    {
      "name": "Kanishka Chholak",
      "designation": "Design Team Volunteer",
      "file": "volunteer_certificates.pdf",
      "page": 171
    },
    {
      "name": "Manish Kumar",
      "designation": "Coverage Team Volunteer",
      "file": "volunteer_certificates.pdf",
      "page": 172
    },
    {
      "name": "Yashaswa Mathur",
      "designation": "Coverage Team Volunteer",
      "file": "volunteer_certificates.pdf",
      "page": 173
    },
    {
      "name": "Pankaj Kumar Meena",
      "designation": "Coverage Team Volunteer",
      "file": "volunteer_certificates.pdf",
      "page": 174
    },
    {
      "name": "Shraman Roy",
      "designation": "Coverage Team Volunteer",
      "file": "volunteer_certificates.pdf",
      "page": 175
    },
    {
      "name": "Induj Tyagi",
      "designation": "Coverage Team Volunteer",
      "file": "volunteer_certificates.pdf",
      "page": 176
    },
    {
      "name": "Gaurav Singh",
      "designation": "Coverage Team Volunteer",
      "file": "volunteer_certificates.pdf",
      "page": 177
    },
    {
      "name": "Anmol Ratan Srivastav",
      "designation": "Public Relation Team Volunteer",
      "file": "volunteer_certificates.pdf",
      "page": 178
    },
    {
      "name": "Uday Prakash Makija",
      "designation": "Public Relation Team Volunteer",
      "file": "volunteer_certificates.pdf",
      "page": 179
    },
    {
      "name": "Harsh Agarwal",
      "designation": "Public Relation Team Volunteer",
      "file": "volunteer_certificates.pdf",
      "page": 180
    },
    {
      "name": "Aayush Kumar",
      "designation": "Public Relation Team Volunteer",
      "file": "volunteer_certificates.pdf",
      "page": 181
    },
    {
      "name": "Rishiraj Mishra",
      "designation": "Public Relation Team Volunteer",
      "file": "volunteer_certificates.pdf",
      "page": 182
    },
    {
      "name": "Shreysa",
      "designation": "Public Relation Team Volunteer",
      "file": "volunteer_certificates.pdf",
      "page": 183
    },
    {
      "name": "Akshat Rai",
      "designation": "Public Relation Team Volunteer",
      "file": "volunteer_certificates.pdf",
      "page": 184
    },
    {
      "name": "Saksham Manu Shukla",
      "designation": "Public Relation Team Volunteer",
      "file": "volunteer_certificates.pdf",
      "page": 185
    },
    {
      "name": "Harsh Singh",
      "designation": "Public Relation Team Volunteer",
      "file": "volunteer_certificates.pdf",
      "page": 186
    },
    {
      "name": "Sparsh Dubey",
      "designation": "Public Relation Team Volunteer",
      "file": "volunteer_certificates.pdf",
      "page": 187
    },
    {
      "name": "Manthan Singla",
      "designation": "Public Relation Team Volunteer",
      "file": "volunteer_certificates.pdf",
      "page": 188
    },
    {
      "name": "Prateek Shukla",
      "designation": "Public Relation Team Volunteer",
      "file": "volunteer_certificates.pdf",
      "page": 189
    },
    {
      "name": "Kanhiya Agrawal",
      "designation": "Public Relation Team Volunteer",
      "file": "volunteer_certificates.pdf",
      "page": 190
    },
    {
      "name": "Akash Das",
      "designation": "Web Development Team Volunteer",
      "file": "volunteer_certificates.pdf",
      "page": 191
    },
    {
      "name": "Muhammad Saad Haider",
      "designation": "Web Development Team Volunteer",
      "file": "volunteer_certificates.pdf",
      "page": 192
    },
    {
      "name": "Ronak Bagri",
      "designation": "Web Development Team Volunteer",
      "file": "volunteer_certificates.pdf",
      "page": 193
    },
    {
      "name": "Aman Pathak",
      "designation": "Web Development Team Volunteer",
      "file": "volunteer_certificates.pdf",
      "page": 194
    },
    {
      "name": "Vikash",
      "designation": "Web Development Team Volunteer",
      "file": "volunteer_certificates.pdf",
      "page": 195
    },
    {
      "name": "Alok Kumar Swarnakar",
      "designation": "Painting Exhibition Team Head",
      "file": "volunteer_certificates.pdf",
      "page": 196
    },
    {
      "name": "Tanu Tanania",
      "designation": "Painting Exhibition Team Volunteer",
      "file": "volunteer_certificates.pdf",
      "page": 197
    },
    {
      "name": "Misti D Shah",
      "designation": "Painting Exhibition Team Volunteer",
      "file": "volunteer_certificates.pdf",
      "page": 198
    },
    {
      "name": "Ashish parmar",
      "designation": "Painting Exhibition Team Volunteer",
      "file": "volunteer_certificates.pdf",
      "page": 199
    },
    {
      "name": "Aastha",
      "designation": "Painting Exhibition Team Volunteer",
      "file": "volunteer_certificates.pdf",
      "page": 200
    },
    {
      "name": "Kishan Kumar",
      "designation": "Painting Exhibition Team Volunteer",
      "file": "volunteer_certificates.pdf",
      "page": 201
    },
    {
      "name": "Sahil",
      "designation": "Tinker's Lab Stall Head",
      "file": "volunteer_certificates.pdf",
      "page": 202
    },
    {
      "name": "Bhanu Pratap",
      "designation": "Tinker's Lab Stall Volunteer",
      "file": "volunteer_certificates.pdf",
      "page": 203
    },
    {
      "name": "Aryan Singh",
      "designation": "Tinker's Lab Stall Volunteer",
      "file": "volunteer_certificates.pdf",
      "page": 204
    },
    {
      "name": "Yash",
      "designation": "Tinker's Lab Stall Volunteer",
      "file": "volunteer_certificates.pdf",
      "page": 205
    },
    {
      "name": "Subhasis Malik",
      "designation": "Tinker's Lab Stall Volunteer",
      "file": "volunteer_certificates.pdf",
      "page": 206
    },
    {
      "name": "Rahul Das",
      "designation": "Tinker's Lab Stall Volunteer",
      "file": "volunteer_certificates.pdf",
      "page": 207
    },
    {
      "name": "Adwait Deshpande",
      "designation": "Tinker's Lab Stall Volunteer",
      "file": "volunteer_certificates.pdf",
      "page": 208
    },
    {
      "name": "Yatindra Shukla",
      "designation": "Tinker's Lab Stall Volunteer",
      "file": "volunteer_certificates.pdf",
      "page": 209
    },
    {
      "name": "Chethan Sai Kumar",
      "designation": "Tinker's Lab Stall Volunteer",
      "file": "volunteer_certificates.pdf",
      "page": 210
    },
    {
      "name": "Bhavishya",
      "designation": "Tinker's Lab Stall Volunteer",
      "file": "volunteer_certificates.pdf",
      "page": 211
    },
    {
      "name": "Rachit Goel",
      "designation": "Tinker's Lab Stall Volunteer",
      "file": "volunteer_certificates.pdf",
      "page": 212
    },
    {
      "name": "Ronak Bagri",
      "designation": "Tinker's Lab Stall Volunteer",
      "file": "volunteer_certificates.pdf",
      "page": 213
    },
    {
      "name": "Kshitij Aryan",
      "designation": "Tinker's Lab Stall Volunteer",
      "file": "volunteer_certificates.pdf",
      "page": 214
    },
    {
      "name": "Harsh Singh",
      "designation": "Tinker's Lab Stall Volunteer",
      "file": "volunteer_certificates.pdf",
      "page": 215
    },
    {
      "name": "Dr. Shirsha Bose",
      "designation": "Biosciences and Bioengineering Stall Head",
      "file": "volunteer_certificates.pdf",
      "page": 216
    },
    {
      "name": "Dr. Manoj Kumar",
      "designation": "Biosciences and Bioengineering Stall Volunteer",
      "file": "volunteer_certificates.pdf",
      "page": 217
    },
    {
      "name": "Mr. Shubham Sharma",
      "designation": "Biosciences and Bioengineering Stall Volunteer",
      "file": "volunteer_certificates.pdf",
      "page": 218
    },
    {
      "name": "Mr. Sathish Tiruveedhula",
      "designation": "Biosciences and Bioengineering Stall Volunteer",
      "file": "volunteer_certificates.pdf",
      "page": 219
    },
    {
      "name": "Ms S Prangya",
      "designation": "Biosciences and Bioengineering Stall Volunteer",
      "file": "volunteer_certificates.pdf",
      "page": 220
    },
    {
      "name": "Mr. Amir Ashraf",
      "designation": "Biosciences and Bioengineering Stall Volunteer",
      "file": "volunteer_certificates.pdf",
      "page": 221
    },
    {
      "name": "Mr. Vikash Kumar",
      "designation": "Electrical Engineering Stall Head",
      "file": "volunteer_certificates.pdf",
      "page": 222
    },
    {
      "name": "Mr. Apoorv Raj Agarwal",
      "designation": "Electrical Engineering Stall Volunteer",
      "file": "volunteer_certificates.pdf",
      "page": 223
    },
    {
      "name": "Mr. Lokesh Sharma",
      "designation": "Electrical Engineering Stall Volunteer",
      "file": "volunteer_certificates.pdf",
      "page": 224
    },
    {
      "name": "Mr. Gautam Kumar",
      "designation": "Electrical Engineering Stall Volunteer",
      "file": "volunteer_certificates.pdf",
      "page": 225
    },
    {
      "name": "Mrs. Taruna Kumari",
      "designation": "Electrical Engineering Stall Volunteer",
      "file": "volunteer_certificates.pdf",
      "page": 226
    },
    {
      "name": "Dr. Shirsendu Ghosh",
      "designation": "Chemistry Lab Stall Head",
      "file": "volunteer_certificates.pdf",
      "page": 227
    },
    {
      "name": "Dr. Piyush Kumar",
      "designation": "Chemistry Lab Stall Volunteer",
      "file": "volunteer_certificates.pdf",
      "page": 228
    },
    {
      "name": "Bhupinder Singh",
      "designation": "Chemistry Lab Stall Volunteer",
      "file": "volunteer_certificates.pdf",
      "page": 229
    },
    {
      "name": "Alok Kr. Swarnkar",
      "designation": "Chemistry Lab Stall Volunteer",
      "file": "volunteer_certificates.pdf",
      "page": 230
    },
    {
      "name": "Dharmander",
      "designation": "Chemistry Lab Stall Volunteer",
      "file": "volunteer_certificates.pdf",
      "page": 231
    },
    {
      "name": "Divya Kumari",
      "designation": "Chemistry Lab Stall Volunteer",
      "file": "volunteer_certificates.pdf",
      "page": 232
    },
    {
      "name": "Ganesh Balu Patil",
      "designation": "Chemistry Lab Stall Volunteer",
      "file": "volunteer_certificates.pdf",
      "page": 233
    },
    {
      "name": "Madhurendra Kr. Pandey",
      "designation": "Chemistry Lab Stall Volunteer",
      "file": "volunteer_certificates.pdf",
      "page": 234
    },
    {
      "name": "Monika",
      "designation": "Chemistry Lab Stall Volunteer",
      "file": "volunteer_certificates.pdf",
      "page": 235
    },
    {
      "name": "Shariq Ajmal",
      "designation": "Chemistry Lab Stall Volunteer",
      "file": "volunteer_certificates.pdf",
      "page": 236
    },
    {
      "name": "Vidhi Patni",
      "designation": "Chemistry Lab Stall Volunteer",
      "file": "volunteer_certificates.pdf",
      "page": 237
    },
    {
      "name": "Abhishek Pratap Singh",
      "designation": "Chemistry Lab Stall Volunteer",
      "file": "volunteer_certificates.pdf",
      "page": 238
    },
    {
      "name": "Akshdeep Chaudhary",
      "designation": "Chemistry Lab Stall Volunteer",
      "file": "volunteer_certificates.pdf",
      "page": 239
    },
    {
      "name": "Ankit Dhiman",
      "designation": "Chemistry Lab Stall Volunteer",
      "file": "volunteer_certificates.pdf",
      "page": 240
    },
    {
      "name": "Tamanna Yadav",
      "designation": "Chemistry Lab Stall Volunteer",
      "file": "volunteer_certificates.pdf",
      "page": 241
    },
    {
      "name": "Vishan Kumar Varma",
      "designation": "Chemistry Lab Stall Volunteer",
      "file": "volunteer_certificates.pdf",
      "page": 242
    }
  ]
}